{
  "product_code": "1012Main",
  "daily": [
    {
      "date": "2026-03-31",
      "avg": 2.695,
      "median": 2.69,
      "p10": 2.39,
      "p90": 2.99,
      "store_count": 7487,
      "availability_pct": 90.82
    },
    {
      "date": "2026-04-01",
      "avg": 2.6952,
      "median": 2.69,
      "p10": 2.39,
      "p90": 2.99,
      "store_count": 7485,
      "availability_pct": 90.79
    },
    {
      "date": "2026-04-02",
      "avg": 2.6952,
      "median": 2.69,
      "p10": 2.39,
      "p90": 2.99,
      "store_count": 7488,
      "availability_pct": 90.83
    },
    {
      "date": "2026-04-03",
      "avg": 2.6948,
      "median": 2.69,
      "p10": 2.39,
      "p90": 2.99,
      "store_count": 7512,
      "availability_pct": 91.12
    },
    {
      "date": "2026-04-04",
      "avg": 2.6947,
      "median": 2.69,
      "p10": 2.39,
      "p90": 2.99,
      "store_count": 7510,
      "availability_pct": 91.1
    },
    {
      "date": "2026-04-05",
      "avg": 2.6944,
      "median": 2.69,
      "p10": 2.39,
      "p90": 2.99,
      "store_count": 7490,
      "availability_pct": 90.85
    },
    {
      "date": "2026-04-06",
      "avg": 2.6945,
      "median": 2.69,
      "p10": 2.39,
      "p90": 2.99,
      "store_count": 7488,
      "availability_pct": 90.83
    },
    {
      "date": "2026-04-07",
      "avg": 2.6942,
      "median": 2.69,
      "p10": 2.39,
      "p90": 2.99,
      "store_count": 7502,
      "availability_pct": 91.0
    },
    {
      "date": "2026-04-08",
      "avg": 2.6942,
      "median": 2.69,
      "p10": 2.39,
      "p90": 2.99,
      "store_count": 7507,
      "availability_pct": 91.06
    },
    {
      "date": "2026-04-09",
      "avg": 2.6944,
      "median": 2.69,
      "p10": 2.39,
      "p90": 2.99,
      "store_count": 7512,
      "availability_pct": 91.12
    },
    {
      "date": "2026-04-10",
      "avg": 2.6944,
      "median": 2.69,
      "p10": 2.39,
      "p90": 2.99,
      "store_count": 7514,
      "availability_pct": 91.15
    },
    {
      "date": "2026-04-11",
      "avg": 2.6941,
      "median": 2.69,
      "p10": 2.39,
      "p90": 2.99,
      "store_count": 7518,
      "availability_pct": 91.19
    },
    {
      "date": "2026-04-12",
      "avg": 2.6943,
      "median": 2.69,
      "p10": 2.39,
      "p90": 2.99,
      "store_count": 7509,
      "availability_pct": 91.08
    },
    {
      "date": "2026-04-13",
      "avg": 2.6942,
      "median": 2.69,
      "p10": 2.39,
      "p90": 2.99,
      "store_count": 7502,
      "availability_pct": 91.0
    },
    {
      "date": "2026-04-14",
      "avg": 2.6943,
      "median": 2.69,
      "p10": 2.39,
      "p90": 2.99,
      "store_count": 7497,
      "availability_pct": 90.94
    },
    {
      "date": "2026-04-15",
      "avg": 2.6943,
      "median": 2.69,
      "p10": 2.39,
      "p90": 2.99,
      "store_count": 7498,
      "availability_pct": 90.95
    },
    {
      "date": "2026-04-17",
      "avg": 2.7166,
      "median": 2.79,
      "p10": 2.39,
      "p90": 2.99,
      "store_count": 7504,
      "availability_pct": 91.02
    },
    {
      "date": "2026-04-18",
      "avg": 2.7165,
      "median": 2.79,
      "p10": 2.39,
      "p90": 2.99,
      "store_count": 7503,
      "availability_pct": 91.01
    },
    {
      "date": "2026-04-19",
      "avg": 2.7166,
      "median": 2.79,
      "p10": 2.39,
      "p90": 2.99,
      "store_count": 7494,
      "availability_pct": 90.9
    },
    {
      "date": "2026-04-20",
      "avg": 2.7168,
      "median": 2.79,
      "p10": 2.39,
      "p90": 2.99,
      "store_count": 7497,
      "availability_pct": 90.94
    },
    {
      "date": "2026-04-21",
      "avg": 2.7171,
      "median": 2.79,
      "p10": 2.39,
      "p90": 2.99,
      "store_count": 7506,
      "availability_pct": 91.05
    },
    {
      "date": "2026-04-22",
      "avg": 2.7168,
      "median": 2.79,
      "p10": 2.39,
      "p90": 2.99,
      "store_count": 7507,
      "availability_pct": 91.06
    },
    {
      "date": "2026-04-23",
      "avg": 2.7169,
      "median": 2.79,
      "p10": 2.39,
      "p90": 2.99,
      "store_count": 7510,
      "availability_pct": 91.1
    },
    {
      "date": "2026-04-24",
      "avg": 2.7168,
      "median": 2.79,
      "p10": 2.39,
      "p90": 2.99,
      "store_count": 7511,
      "availability_pct": 91.11
    },
    {
      "date": "2026-04-25",
      "avg": 2.7168,
      "median": 2.79,
      "p10": 2.39,
      "p90": 2.99,
      "store_count": 7511,
      "availability_pct": 91.11
    },
    {
      "date": "2026-04-26",
      "avg": 2.7168,
      "median": 2.79,
      "p10": 2.39,
      "p90": 2.99,
      "store_count": 7511,
      "availability_pct": 91.11
    },
    {
      "date": "2026-04-27",
      "avg": 2.7171,
      "median": 2.79,
      "p10": 2.39,
      "p90": 2.99,
      "store_count": 7500,
      "availability_pct": 90.98
    },
    {
      "date": "2026-04-28",
      "avg": 2.717,
      "median": 2.79,
      "p10": 2.39,
      "p90": 2.99,
      "store_count": 7500,
      "availability_pct": 90.96
    },
    {
      "date": "2026-04-29",
      "avg": 2.7177,
      "median": 2.79,
      "p10": 2.39,
      "p90": 2.99,
      "store_count": 7501,
      "availability_pct": 90.98
    },
    {
      "date": "2026-04-30",
      "avg": 2.7178,
      "median": 2.79,
      "p10": 2.39,
      "p90": 2.99,
      "store_count": 7507,
      "availability_pct": 91.02
    },
    {
      "date": "2026-05-01",
      "avg": 2.7178,
      "median": 2.79,
      "p10": 2.39,
      "p90": 2.99,
      "store_count": 7511,
      "availability_pct": 91.06
    },
    {
      "date": "2026-05-02",
      "avg": 2.7176,
      "median": 2.79,
      "p10": 2.39,
      "p90": 2.99,
      "store_count": 7515,
      "availability_pct": 91.11
    },
    {
      "date": "2026-05-03",
      "avg": 2.7128,
      "median": 2.69,
      "p10": 2.39,
      "p90": 2.99,
      "store_count": 3136,
      "availability_pct": 38.02
    },
    {
      "date": "2026-05-04",
      "avg": 2.7177,
      "median": 2.79,
      "p10": 2.39,
      "p90": 2.99,
      "store_count": 7510,
      "availability_pct": 91.05
    },
    {
      "date": "2026-05-05",
      "avg": 2.7151,
      "median": 2.79,
      "p10": 2.49,
      "p90": 2.99,
      "store_count": 3675,
      "availability_pct": 44.56
    },
    {
      "date": "2026-05-06",
      "avg": 2.7183,
      "median": 2.79,
      "p10": 2.49,
      "p90": 2.99,
      "store_count": 7514,
      "availability_pct": 91.1
    }
  ],
  "events": []
}