{
  "product_code": "22609",
  "daily": [
    {
      "date": "2026-03-31",
      "avg": 10.3408,
      "median": 10.29,
      "p10": 9.29,
      "p90": 11.59,
      "store_count": 7622,
      "availability_pct": 92.46
    },
    {
      "date": "2026-04-01",
      "avg": 10.3415,
      "median": 10.29,
      "p10": 9.29,
      "p90": 11.59,
      "store_count": 7611,
      "availability_pct": 92.32
    },
    {
      "date": "2026-04-02",
      "avg": 10.3421,
      "median": 10.29,
      "p10": 9.29,
      "p90": 11.59,
      "store_count": 7611,
      "availability_pct": 92.32
    },
    {
      "date": "2026-04-03",
      "avg": 10.3439,
      "median": 10.29,
      "p10": 9.29,
      "p90": 11.59,
      "store_count": 7590,
      "availability_pct": 92.07
    },
    {
      "date": "2026-04-04",
      "avg": 10.3438,
      "median": 10.29,
      "p10": 9.21,
      "p90": 11.59,
      "store_count": 7593,
      "availability_pct": 92.1
    },
    {
      "date": "2026-04-05",
      "avg": 10.3446,
      "median": 10.29,
      "p10": 9.29,
      "p90": 11.59,
      "store_count": 7589,
      "availability_pct": 92.05
    },
    {
      "date": "2026-04-06",
      "avg": 10.3449,
      "median": 10.29,
      "p10": 9.29,
      "p90": 11.59,
      "store_count": 7575,
      "availability_pct": 91.89
    },
    {
      "date": "2026-04-07",
      "avg": 10.3455,
      "median": 10.29,
      "p10": 9.29,
      "p90": 11.59,
      "store_count": 7570,
      "availability_pct": 91.82
    },
    {
      "date": "2026-04-08",
      "avg": 10.345,
      "median": 10.29,
      "p10": 9.29,
      "p90": 11.59,
      "store_count": 7578,
      "availability_pct": 91.92
    },
    {
      "date": "2026-04-09",
      "avg": 10.3447,
      "median": 10.29,
      "p10": 9.29,
      "p90": 11.59,
      "store_count": 7586,
      "availability_pct": 92.02
    },
    {
      "date": "2026-04-10",
      "avg": 10.3447,
      "median": 10.29,
      "p10": 9.29,
      "p90": 11.59,
      "store_count": 7587,
      "availability_pct": 92.03
    },
    {
      "date": "2026-04-11",
      "avg": 10.3448,
      "median": 10.29,
      "p10": 9.29,
      "p90": 11.59,
      "store_count": 7584,
      "availability_pct": 91.99
    },
    {
      "date": "2026-04-12",
      "avg": 10.3446,
      "median": 10.29,
      "p10": 9.29,
      "p90": 11.59,
      "store_count": 7579,
      "availability_pct": 91.93
    },
    {
      "date": "2026-04-13",
      "avg": 10.3445,
      "median": 10.29,
      "p10": 9.29,
      "p90": 11.59,
      "store_count": 7570,
      "availability_pct": 91.82
    },
    {
      "date": "2026-04-14",
      "avg": 10.3455,
      "median": 10.29,
      "p10": 9.29,
      "p90": 11.59,
      "store_count": 7570,
      "availability_pct": 91.82
    },
    {
      "date": "2026-04-15",
      "avg": 10.3486,
      "median": 10.29,
      "p10": 9.29,
      "p90": 11.59,
      "store_count": 7573,
      "availability_pct": 91.86
    },
    {
      "date": "2026-04-17",
      "avg": 10.4057,
      "median": 10.29,
      "p10": 9.29,
      "p90": 11.59,
      "store_count": 7613,
      "availability_pct": 92.35
    },
    {
      "date": "2026-04-18",
      "avg": 10.4064,
      "median": 10.29,
      "p10": 9.29,
      "p90": 11.59,
      "store_count": 7599,
      "availability_pct": 92.18
    },
    {
      "date": "2026-04-19",
      "avg": 10.4061,
      "median": 10.29,
      "p10": 9.29,
      "p90": 11.59,
      "store_count": 7546,
      "availability_pct": 91.53
    },
    {
      "date": "2026-04-20",
      "avg": 10.4072,
      "median": 10.29,
      "p10": 9.29,
      "p90": 11.59,
      "store_count": 7490,
      "availability_pct": 90.85
    },
    {
      "date": "2026-04-21",
      "avg": 10.4056,
      "median": 10.29,
      "p10": 9.29,
      "p90": 11.59,
      "store_count": 7497,
      "availability_pct": 90.94
    },
    {
      "date": "2026-04-22",
      "avg": 10.4064,
      "median": 10.29,
      "p10": 9.29,
      "p90": 11.59,
      "store_count": 7520,
      "availability_pct": 91.22
    },
    {
      "date": "2026-04-23",
      "avg": 10.4078,
      "median": 10.29,
      "p10": 9.29,
      "p90": 11.59,
      "store_count": 7536,
      "availability_pct": 91.41
    },
    {
      "date": "2026-04-24",
      "avg": 10.4076,
      "median": 10.29,
      "p10": 9.29,
      "p90": 11.59,
      "store_count": 7538,
      "availability_pct": 91.44
    },
    {
      "date": "2026-04-25",
      "avg": 10.4069,
      "median": 10.29,
      "p10": 9.29,
      "p90": 11.59,
      "store_count": 7539,
      "availability_pct": 91.45
    },
    {
      "date": "2026-04-26",
      "avg": 10.4069,
      "median": 10.29,
      "p10": 9.29,
      "p90": 11.59,
      "store_count": 7539,
      "availability_pct": 91.45
    },
    {
      "date": "2026-04-27",
      "avg": 10.4082,
      "median": 10.29,
      "p10": 9.29,
      "p90": 11.59,
      "store_count": 7492,
      "availability_pct": 90.88
    },
    {
      "date": "2026-04-28",
      "avg": 10.4078,
      "median": 10.29,
      "p10": 9.29,
      "p90": 11.59,
      "store_count": 7502,
      "availability_pct": 90.99
    },
    {
      "date": "2026-04-29",
      "avg": 10.408,
      "median": 10.29,
      "p10": 9.29,
      "p90": 11.59,
      "store_count": 7504,
      "availability_pct": 91.01
    },
    {
      "date": "2026-04-30",
      "avg": 10.407,
      "median": 10.29,
      "p10": 9.29,
      "p90": 11.59,
      "store_count": 7519,
      "availability_pct": 91.16
    },
    {
      "date": "2026-05-01",
      "avg": 10.4064,
      "median": 10.29,
      "p10": 9.29,
      "p90": 11.59,
      "store_count": 7532,
      "availability_pct": 91.32
    },
    {
      "date": "2026-05-02",
      "avg": 10.4059,
      "median": 10.29,
      "p10": 9.29,
      "p90": 11.59,
      "store_count": 7508,
      "availability_pct": 91.03
    },
    {
      "date": "2026-05-03",
      "avg": 10.4049,
      "median": 10.29,
      "p10": 9.29,
      "p90": 11.69,
      "store_count": 3125,
      "availability_pct": 37.89
    },
    {
      "date": "2026-05-04",
      "avg": 10.4073,
      "median": 10.29,
      "p10": 9.29,
      "p90": 11.59,
      "store_count": 7464,
      "availability_pct": 90.49
    },
    {
      "date": "2026-05-05",
      "avg": 10.4068,
      "median": 10.29,
      "p10": 9.39,
      "p90": 11.59,
      "store_count": 3668,
      "availability_pct": 44.47
    },
    {
      "date": "2026-05-06",
      "avg": 10.4111,
      "median": 10.29,
      "p10": 9.29,
      "p90": 11.59,
      "store_count": 7495,
      "availability_pct": 90.87
    },
    {
      "date": "2026-05-07",
      "avg": 10.411,
      "median": 10.29,
      "p10": 9.29,
      "p90": 11.59,
      "store_count": 7513,
      "availability_pct": 91.07
    },
    {
      "date": "2026-05-08",
      "avg": 10.4102,
      "median": 10.29,
      "p10": 9.29,
      "p90": 11.59,
      "store_count": 7516,
      "availability_pct": 91.1
    },
    {
      "date": "2026-05-09",
      "avg": 10.4111,
      "median": 10.29,
      "p10": 9.29,
      "p90": 11.59,
      "store_count": 7522,
      "availability_pct": 91.18
    },
    {
      "date": "2026-05-10",
      "avg": 10.41,
      "median": 10.29,
      "p10": 9.29,
      "p90": 11.59,
      "store_count": 7498,
      "availability_pct": 90.88
    }
  ],
  "events": []
}